[
  { "kind": "folder", "label": "Geography / All decks", "subject": "Geography" },

  { "kind": "folder", "label": "Geography / Prelim (Soils / Coasts / Climate)", "subject": "Geography" },

  {
    "kind": "deck",
    "label": "Geography / Prelim (Soils / Coasts / Climate) / Soils",
    "subject": "Geography",
    "topic": "Prelim (Soils / Coasts / Climate)",
    "deck": "Soils (Brown earth / Podzol / Gley)",
    "file": "decks/geography/isla_prelim_soils.json"
  },
  {
    "kind": "deck",
    "label": "Geography / Prelim (Soils / Coasts / Climate) / Coasts",
    "subject": "Geography",
    "topic": "Prelim (Soils / Coasts / Climate)",
    "deck": "Coasts (Processes + Landforms)",
    "file": "decks/geography/isla_prelim_coasts.json"
  },
  {
    "kind": "deck",
    "label": "Geography / Prelim (Soils / Coasts / Climate) / Climate Change",
    "subject": "Geography",
    "topic": "Prelim (Soils / Coasts / Climate)",
    "deck": "Global Climate Change (Causes / Effects / Management)",
    "file": "decks/geography/isla_prelim_climate_change.json"
  },

  {
    "kind": "deck",
    "label": "Geography / Core terms / Physical and environment",
    "subject": "Geography",
    "topic": "Core terms",
    "deck": "Physical and environment",
    "file": "decks/geography/physical_and_environment.json"
  },
  {
    "kind": "deck",
    "label": "Geography / Core terms / Human and development",
    "subject": "Geography",
    "topic": "Core terms",
    "deck": "Human and development",
    "file": "decks/geography/human_and_development.json"
  }
]
